Voodoo-1.6.0.dist-info/DESCRIPTION.rst
Voodoo-1.6.0.dist-info/METADATA
Voodoo-1.6.0.dist-info/RECORD
Voodoo-1.6.0.dist-info/WHEEL
Voodoo-1.6.0.dist-info/entry_points.txt
Voodoo-1.6.0.dist-info/metadata.json
Voodoo-1.6.0.dist-info/top_level.txt
tests/__init__.py
tests/conftest.py
tests/helpers.py
tests/test_output.py
tests/test_prompt.py
tests/test_render.py
tests/test_vcs.py
voodoo/__init__.py
voodoo/_compat.py
voodoo/cli.py
voodoo/helpers.py
voodoo/main.py
voodoo/script.py
voodoo/vcs.py
