Metadata-Version: 2.0
Name: Voodoo
Version: 1.6.0
Summary: Template system for project skeletons
Home-page: http://github.com/jpscaletti/voodoo
Author: Juan-Pablo Scaletti
Author-email: juanpablo@jpscaletti.com
License: BSD license (see LICENSE)
Platform: UNKNOWN
Classifier: Development Status :: 4 - Beta
Classifier: Environment :: Web Environment
Classifier: Intended Audience :: Developers
Classifier: License :: OSI Approved :: BSD License
Classifier: Operating System :: OS Independent
Classifier: Programming Language :: Python
Classifier: Programming Language :: Python :: 2
Classifier: Programming Language :: Python :: 2.6
Classifier: Programming Language :: Python :: 2.7
Classifier: Programming Language :: Python :: 3
Classifier: Programming Language :: Python :: 3.3
Classifier: Topic :: Internet :: WWW/HTTP :: Dynamic Content
Classifier: Topic :: Software Development :: Libraries :: Python Modules
Requires-Dist: jinja2 (>=2.7)
Requires-Dist: colorama (>=0.2.5)
Requires-Dist: Baker (>=1.3)
